.gitignore
README.md
pyproject.toml
spec/__init__.py
spec/default.py
spec/exception.py
spec/ext/__init__.py
spec/ext/endpoint.py
spec/ext/middleware.py
spec/ext/testing.py
spec/fn.py
spec/loader.py
spec/types.py
tests/__init__.py
tests/conftest.py
tests/mock.toml
tests/test_module.py
tests/test_sentry.py
tests/test_socket.py
tests/test_spec.py
tests/test_version.py
dep_spec-2.3.29.dist-info/WHEEL
dep_spec-2.3.29.dist-info/METADATA
dep_spec-2.3.29.dist-info/RECORD
