Metadata-Version: 2.1
Name: dep-spec
Version: 2.3.29
Summary: 
Author: everhide
Author-email: i.tolkachnikov@gmail.com
Requires-Python: >=3.9,<=3.11
Classifier: Programming Language :: Python :: 3
Classifier: Programming Language :: Python :: 3.10
Classifier: Programming Language :: Python :: 3.9
Requires-Dist: Faker (>=14.0.0,<15.0.0)
Requires-Dist: fastapi (>=0.79.0,<0.80.0)
Requires-Dist: fastapi-jsonrpc (>=2.3.0,<3.0.0)
Requires-Dist: poetry (==1.1.15)
Requires-Dist: python-dotenv (>=0.20.0,<0.21.0)
Requires-Dist: uvicorn (>=0.18.2,<0.19.0)
